yta_google_api/__init__.py
yta_google_api/oauth/__init__.py
yta_google_api/oauth/google_oauth_api.py
yta_google_api-0.0.7.dist-info/LICENSE
yta_google_api-0.0.7.dist-info/METADATA
yta_google_api-0.0.7.dist-info/WHEEL
yta_google_api-0.0.7.dist-info/RECORD
