Metadata-Version: 2.3
Name: yta-google-api
Version: 0.0.7
Summary: Google API services simplified.
Author: danialcala94
Author-email: danielalcalavalera@gmail.com
Requires-Python: ==3.9
Classifier: Programming Language :: Python :: 3
Classifier: Programming Language :: Python :: 3.9
Requires-Dist: google-api-python-client (>=2.108.0,<3.0.0)
Requires-Dist: google-auth (>=2.30.0,<3.0.0)
Requires-Dist: google_auth_oauthlib (>=0.4.6,<1.0.0)
Requires-Dist: yta_general_utils (>=0.0.251,<0.1.0)
